batman
tests
