Metadata-Version: 1.1
Name: Batman
Version: 0.6.1
Summary: A deployment toolbelt
Home-page: https://github.com/realgeeks/batman
Author: Kevin McCarthy
Author-email: me@kevinmccarthy.org
License: MIT
Platform: UNKNOWN
Classifier: Development Status :: 4 - Beta
Classifier: Environment :: Console
Classifier: Intended Audience :: Developers
Classifier: Programming Language :: Python
Classifier: Topic :: System :: Installation/Setup
Classifier: Topic :: Software Development :: Version Control
Classifier: License :: OSI Approved :: MIT License
